CLA/cla.v
module cla(a, b, s, cin, cout);

    input [3:0] a;
    input [3:0] b;
    input cin;
    
    output cout;
    output [3:0] s;

    //Gs

    and(g0, a[0], b[0]);
    and(g1, a[1], b[1]);
    and(g2, a[2], b[2]);
    and(g3, a[3], b[3]);

    //Ps

    xor(p0, a[0], b[0]);
    xor(p1, a[1], b[1]);
    xor(p2, a[2], b[2]);    
    xor(p3, a[3], b[3]);

    //Cs

    and(p0cin,p0,cin);
    or(c1,p0cin,g0);

    and(p1p0cin,p1,p0,cin);
    and(p1g0,p1,g0);
    or(c2,g1,p1g0,p1p0cin);

    and(p2p1p0cin,p2,p1,p0,cin);
    and(p2p1g0,p2,p1,g0);
    and(p2g1,p2,g1);
    or(c3,p2p1p0cin,p2p1g0,p2g1,g2);

    and(p3p2p1p0cin,p3,p2,p1,p0,cin);
    and(p3p2p1g0,p3,p2,p1,g0);
    and(p3p2g1,p3,p2,g1);
    and(p3g2,p3,g2);
    or(cout,p3p2p1p0cin,p3p2p1g0,p3p2g1,p3g2,g3);

    //Ss

    xor(s[0], p0, cin);
    xor(s[1], p1, c1);    
    xor(s[2], p2, c2);
    xor(s[3], p3, c3);

endmodule

CLA/cla_tb.v
`include "cla.v"

module cla_tb();

reg [3:0] a,b;
reg cin;
wire [3:0] s;
wire cout;

cla uut(
    .a(a),
    .b(b),
    .s(s),
    .cin(cin),
    .cout(cout)
);

initial begin
    $dumpfile("cla.vcd");
    $dumpvars(0,cla_tb);
    a = 4'b0;
    b = 4'b0;
    cin = 1'b0;

    #256 $finish;
end

always #1 a = a + 1;
always #16 b = b + 1;

endmodule

CLA/cla.vcd
$date
	Mon Dec  6 20:52:59 2021
$end
$version
	Icarus Verilog
$end
$timescale
	1s
$end
$scope module cla_tb $end
$var wire 4 ! s [3:0] $end
$var wire 1 " cout $end
$var reg 4 # a [3:0] $end
$var reg 4 $ b [3:0] $end
$var reg 1 % cin $end
$scope module uut $end
$var wire 4 & a [3:0] $end
$var wire 4 ' b [3:0] $end
$var wire 1 ( c1 $end
$var wire 1 ) c2 $end
$var wire 1 * c3 $end
$var wire 1 % cin $end
$var wire 1 " cout $end
$var wire 1 + g0 $end
$var wire 1 , g1 $end
$var wire 1 - g2 $end
$var wire 1 . g3 $end
$var wire 1 / p0 $end
$var wire 1 0 p0cin $end
$var wire 1 1 p1 $end
$var wire 1 2 p1g0 $end
$var wire 1 3 p1p0cin $end
$var wire 1 4 p2 $end
$var wire 1 5 p2g1 $end
$var wire 1 6 p2p1g0 $end
$var wire 1 7 p2p1p0cin $end
$var wire 1 8 p3 $end
$var wire 1 9 p3g2 $end
$var wire 1 : p3p2g1 $end
$var wire 1 ; p3p2p1g0 $end
$var wire 1 < p3p2p1p0cin $end
$var wire 4 = s [3:0] $end
$upscope $end
$upscope $end
$enddefinitions $end
#0
$dumpvars
b0 =
0<
0;
0:
09
08
07
06
05
04
03
02
01
00
0/
0.
0-
0,
0+
0*
0)
0(
b0 '
b0 &
0%
b0 $
b0 #
0"
b0 !
$end
#1
b1 !
b1 =
1/
b1 #
b1 &
#2
b10 !
b10 =
0/
11
b10 #
b10 &
#3
b11 !
b11 =
1/
b11 #
b11 &
#4
b100 !
b100 =
0/
01
14
b100 #
b100 &
#5
b101 !
b101 =
1/
b101 #
b101 &
#6
b110 !
b110 =
0/
11
b110 #
b110 &
#7
b111 !
b111 =
1/
b111 #
b111 &
#8
b1000 !
b1000 =
0/
01
04
18
b1000 #
b1000 &
#9
b1001 !
b1001 =
1/
b1001 #
b1001 &
#10
b1010 !
b1010 =
0/
11
b1010 #
b1010 &
#11
b1011 !
b1011 =
1/
b1011 #
b1011 &
#12
b1100 !
b1100 =
0/
01
14
b1100 #
b1100 &
#13
b1101 !
b1101 =
1/
b1101 #
b1101 &
#14
b1110 !
b1110 =
0/
11
b1110 #
b1110 &
#15
b1111 !
b1111 =
1/
b1111 #
b1111 &
#16
b1 !
b1 =
01
04
08
b0 #
b0 &
b1 $
b1 '
#17
1(
b10 !
b10 =
1+
0/
b1 #
b1 &
#18
0(
b11 !
b11 =
0+
1/
11
b10 #
b10 &
#19
1)
1(
12
b100 !
b100 =
1+
0/
b11 #
b11 &
#20
0)
0(
02
b101 !
b101 =
0+
1/
01
14
b100 #
b100 &
#21
1(
b110 !
b110 =
1+
0/
b101 #
b101 &
#22
0(
b111 !
b111 =
0+
1/
11
b110 #
b110 &
#23
1)
1*
1(
12
16
b1000 !
b1000 =
1+
0/
b111 #
b111 &
#24
0)
0*
0(
02
06
b1001 !
b1001 =
0+
1/
01
04
18
b1000 #
b1000 &
#25
1(
b1010 !
b1010 =
1+
0/
b1001 #
b1001 &
#26
0(
b1011 !
b1011 =
0+
1/
11
b1010 #
b1010 &
#27
1)
1(
12
b1100 !
b1100 =
1+
0/
b1011 #
b1011 &
#28
0)
0(
02
b1101 !
b1101 =
0+
1/
01
14
b1100 #
b1100 &
#29
1(
b1110 !
b1110 =
1+
0/
b1101 #
b1101 &
#30
0(
b1111 !
b1111 =
0+
1/
11
b1110 #
b1110 &
#31
1"
1)
1*
1(
12
16
1;
b0 !
b0 =
1+
0/
b1111 #
b1111 &
#32
0"
0)
0*
b10 !
b10 =
0(
02
06
0;
04
08
0+
b0 #
b0 &
b10 $
b10 '
#33
b11 !
b11 =
1/
b1 #
b1 &
#34
1)
b100 !
b100 =
1,
0/
01
b10 #
b10 &
#35
b101 !
b101 =
1/
b11 #
b11 &
#36
0)
b110 !
b110 =
0,
0/
11
14
b100 #
b100 &
#37
b111 !
b111 =
1/
b101 #
b101 &
#38
1*
1)
15
b1000 !
b1000 =
1,
0/
01
b110 #
b110 &
#39
b1001 !
b1001 =
1/
b111 #
b111 &
#40
0*
0)
05
b1010 !
b1010 =
0,
0/
11
04
18
b1000 #
b1000 &
#41
b1011 !
b1011 =
1/
b1001 #
b1001 &
#42
1)
b1100 !
b1100 =
1,
0/
01
b1010 #
b1010 &
#43
b1101 !
b1101 =
1/
b1011 #
b1011 &
#44
0)
b1110 !
b1110 =
0,
0/
11
14
b1100 #
b1100 &
#45
b1111 !
b1111 =
1/
b1101 #
b1101 &
#46
1"
1*
1)
15
1:
b0 !
b0 =
1,
0/
01
b1110 #
b1110 &
#47
b1 !
b1 =
1/
b1111 #
b1111 &
#48
0"
0*
0)
05
0:
b11 !
b11 =
0,
11
04
08
b0 #
b0 &
b11 $
b11 '
#49
1)
1(
12
b100 !
b100 =
1+
0/
b1 #
b1 &
#50
0(
02
b101 !
b101 =
0+
1,
1/
01
b10 #
b10 &
#51
1(
b110 !
b110 =
1+
0/
b11 #
b11 &
#52
0(
0)
b111 !
b111 =
0+
0,
1/
11
14
b100 #
b100 &
#53
1)
1*
1(
12
16
b1000 !
b1000 =
1+
0/
b101 #
b101 &
#54
0(
15
02
06
b1001 !
b1001 =
0+
1,
1/
01
b110 #
b110 &
#55
1(
b1010 !
b1010 =
1+
0/
b111 #
b111 &
#56
0*
0(
0)
05
b1011 !
b1011 =
0+
0,
1/
11
04
18
b1000 #
b1000 &
#57
1)
1(
12
b1100 !
b1100 =
1+
0/
b1001 #
b1001 &
#58
0(
02
b1101 !
b1101 =
0+
1,
1/
01
b1010 #
b1010 &
#59
1(
b1110 !
b1110 =
1+
0/
b1011 #
b1011 &
#60
0(
0)
b1111 !
b1111 =
0+
0,
1/
11
14
b1100 #
b1100 &
#61
1"
1)
1*
1(
12
16
1;
b0 !
b0 =
1+
0/
b1101 #
b1101 &
#62
0(
15
1:
02
06
0;
b1 !
b1 =
0+
1,
1/
01
b1110 #
b1110 &
#63
1(
b10 !
b10 =
1+
0/
b1111 #
b1111 &
#64
0"
0*
b100 !
b100 =
0(
0)
05
0:
08
0+
0,
b0 #
b0 &
b100 $
b100 '
#65
b101 !
b101 =
1/
b1 #
b1 &
#66
b110 !
b110 =
0/
11
b10 #
b10 &
#67
b111 !
b111 =
1/
b11 #
b11 &
#68
1*
b1000 !
b1000 =
1-
0/
01
04
b100 #
b100 &
#69
b1001 !
b1001 =
1/
b101 #
b101 &
#70
b1010 !
b1010 =
0/
11
b110 #
b110 &
#71
b1011 !
b1011 =
1/
b111 #
b111 &
#72
0*
b1100 !
b1100 =
0-
0/
01
14
18
b1000 #
b1000 &
#73
b1101 !
b1101 =
1/
b1001 #
b1001 &
#74
b1110 !
b1110 =
0/
11
b1010 #
b1010 &
#75
b1111 !
b1111 =
1/
b1011 #
b1011 &
#76
1"
1*
19
b0 !
b0 =
1-
0/
01
04
b1100 #
b1100 &
#77
b1 !
b1 =
1/
b1101 #
b1101 &
#78
b10 !
b10 =
0/
11
b1110 #
b1110 &
#79
b11 !
b11 =
1/
b1111 #
b1111 &
#80
0"
0*
09
b101 !
b101 =
0-
01
14
08
b0 #
b0 &
b101 $
b101 '
#81
1(
b110 !
b110 =
1+
0/
b1 #
b1 &
#82
0(
b111 !
b111 =
0+
1/
11
b10 #
b10 &
#83
1)
1*
1(
12
16
b1000 !
b1000 =
1+
0/
b11 #
b11 &
#84
0)
0(
02
06
b1001 !
b1001 =
0+
1-
1/
01
04
b100 #
b100 &
#85
1(
b1010 !
b1010 =
1+
0/
b101 #
b101 &
#86
0(
b1011 !
b1011 =
0+
1/
11
b110 #
b110 &
#87
1)
1(
12
b1100 !
b1100 =
1+
0/
b111 #
b111 &
#88
0)
0(
0*
02
b1101 !
b1101 =
0+
0-
1/
01
14
18
b1000 #
b1000 &
#89
1(
b1110 !
b1110 =
1+
0/
b1001 #
b1001 &
#90
0(
b1111 !
b1111 =
0+
1/
11
b1010 #
b1010 &
#91
1"
1)
1*
1(
12
16
1;
b0 !
b0 =
1+
0/
b1011 #
b1011 &
#92
0)
0(
19
02
06
0;
b1 !
b1 =
0+
1-
1/
01
04
b1100 #
b1100 &
#93
1(
b10 !
b10 =
1+
0/
b1101 #
b1101 &
#94
0(
b11 !
b11 =
0+
1/
11
b1110 #
b1110 &
#95
1)
1(
12
b100 !
b100 =
1+
0/
b1111 #
b1111 &
#96
0"
0)
0*
09
b110 !
b110 =
0(
02
0-
14
08
0+
b0 #
b0 &
b110 $
b110 '
#97
b111 !
b111 =
1/
b1 #
b1 &
#98
1*
1)
15
b1000 !
b1000 =
1,
0/
01
b10 #
b10 &
#99
b1001 !
b1001 =
1/
b11 #
b11 &
#100
0)
05
b1010 !
b1010 =
0,
1-
0/
11
04
b100 #
b100 &
#101
b1011 !
b1011 =
1/
b101 #
b101 &
#102
1)
b1100 !
b1100 =
1,
0/
01
b110 #
b110 &
#103
b1101 !
b1101 =
1/
b111 #
b111 &
#104
0)
0*
b1110 !
b1110 =
0,
0-
0/
11
14
18
b1000 #
b1000 &
#105
b1111 !
b1111 =
1/
b1001 #
b1001 &
#106
1"
1*
1)
15
1:
b0 !
b0 =
1,
0/
01
b1010 #
b1010 &
#107
b1 !
b1 =
1/
b1011 #
b1011 &
#108
0)
19
05
0:
b10 !
b10 =
0,
1-
0/
11
04
b1100 #
b1100 &
#109
b11 !
b11 =
1/
b1101 #
b1101 &
#110
1)
b100 !
b100 =
1,
0/
01
b1110 #
b1110 &
#111
b101 !
b101 =
1/
b1111 #
b1111 &
#112
0"
0)
0*
09
b111 !
b111 =
0,
0-
11
14
08
b0 #
b0 &
b111 $
b111 '
#113
1)
1*
1(
12
16
b1000 !
b1000 =
1+
0/
b1 #
b1 &
#114
0(
15
02
06
b1001 !
b1001 =
0+
1,
1/
01
b10 #
b10 &
#115
1(
b1010 !
b1010 =
1+
0/
b11 #
b11 &
#116
0(
0)
05
b1011 !
b1011 =
0+
0,
1-
1/
11
04
b100 #
b100 &
#117
1)
1(
12
b1100 !
b1100 =
1+
0/
b101 #
b101 &
#118
0(
02
b1101 !
b1101 =
0+
1,
1/
01
b110 #
b110 &
#119
1(
b1110 !
b1110 =
1+
0/
b111 #
b111 &
#120
0(
0)
0*
b1111 !
b1111 =
0+
0,
0-
1/
11
14
18
b1000 #
b1000 &
#121
1"
1)
1*
1(
12
16
1;
b0 !
b0 =
1+
0/
b1001 #
b1001 &
#122
0(
15
1:
02
06
0;
b1 !
b1 =
0+
1,
1/
01
b1010 #
b1010 &
#123
1(
b10 !
b10 =
1+
0/
b1011 #
b1011 &
#124
0(
0)
19
05
0:
b11 !
b11 =
0+
0,
1-
1/
11
04
b1100 #
b1100 &
#125
1)
1(
12
b100 !
b100 =
1+
0/
b1101 #
b1101 &
#126
0(
02
b101 !
b101 =
0+
1,
1/
01
b1110 #
b1110 &
#127
1(
b110 !
b110 =
1+
0/
b1111 #
b1111 &
#128
0"
b1000 !
b1000 =
0(
0)
0*
09
0+
0,
0-
b0 #
b0 &
b1000 $
b1000 '
#129
b1001 !
b1001 =
1/
b1 #
b1 &
#130
b1010 !
b1010 =
0/
11
b10 #
b10 &
#131
b1011 !
b1011 =
1/
b11 #
b11 &
#132
b1100 !
b1100 =
0/
01
14
b100 #
b100 &
#133
b1101 !
b1101 =
1/
b101 #
b101 &
#134
b1110 !
b1110 =
0/
11
b110 #
b110 &
#135
b1111 !
b1111 =
1/
b111 #
b111 &
#136
1"
b0 !
b0 =
1.
0/
01
04
08
b1000 #
b1000 &
#137
b1 !
b1 =
1/
b1001 #
b1001 &
#138
b10 !
b10 =
0/
11
b1010 #
b1010 &
#139
b11 !
b11 =
1/
b1011 #
b1011 &
#140
b100 !
b100 =
0/
01
14
b1100 #
b1100 &
#141
b101 !
b101 =
1/
b1101 #
b1101 &
#142
b110 !
b110 =
0/
11
b1110 #
b1110 &
#143
b111 !
b111 =
1/
b1111 #
b1111 &
#144
0"
b1001 !
b1001 =
0.
01
04
18
b0 #
b0 &
b1001 $
b1001 '
#145
1(
b1010 !
b1010 =
1+
0/
b1 #
b1 &
#146
0(
b1011 !
b1011 =
0+
1/
11
b10 #
b10 &
#147
1)
1(
12
b1100 !
b1100 =
1+
0/
b11 #
b11 &
#148
0)
0(
02
b1101 !
b1101 =
0+
1/
01
14
b100 #
b100 &
#149
1(
b1110 !
b1110 =
1+
0/
b101 #
b101 &
#150
0(
b1111 !
b1111 =
0+
1/
11
b110 #
b110 &
#151
1"
1)
1*
1(
12
16
1;
b0 !
b0 =
1+
0/
b111 #
b111 &
#152
0)
0*
0(
02
06
0;
b1 !
b1 =
0+
1.
1/
01
04
08
b1000 #
b1000 &
#153
1(
b10 !
b10 =
1+
0/
b1001 #
b1001 &
#154
0(
b11 !
b11 =
0+
1/
11
b1010 #
b1010 &
#155
1)
1(
12
b100 !
b100 =
1+
0/
b1011 #
b1011 &
#156
0)
0(
02
b101 !
b101 =
0+
1/
01
14
b1100 #
b1100 &
#157
1(
b110 !
b110 =
1+
0/
b1101 #
b1101 &
#158
0(
b111 !
b111 =
0+
1/
11
b1110 #
b1110 &
#159
1)
1*
1(
12
16
b1000 !
b1000 =
1+
0/
b1111 #
b1111 &
#160
0"
0)
0*
b1010 !
b1010 =
0(
02
06
0.
04
18
0+
b0 #
b0 &
b1010 $
b1010 '
#161
b1011 !
b1011 =
1/
b1 #
b1 &
#162
1)
b1100 !
b1100 =
1,
0/
01
b10 #
b10 &
#163
b1101 !
b1101 =
1/
b11 #
b11 &
#164
0)
b1110 !
b1110 =
0,
0/
11
14
b100 #
b100 &
#165
b1111 !
b1111 =
1/
b101 #
b101 &
#166
1"
1*
1)
15
1:
b0 !
b0 =
1,
0/
01
b110 #
b110 &
#167
b1 !
b1 =
1/
b111 #
b111 &
#168
0*
0)
05
0:
b10 !
b10 =
0,
1.
0/
11
04
08
b1000 #
b1000 &
#169
b11 !
b11 =
1/
b1001 #
b1001 &
#170
1)
b100 !
b100 =
1,
0/
01
b1010 #
b1010 &
#171
b101 !
b101 =
1/
b1011 #
b1011 &
#172
0)
b110 !
b110 =
0,
0/
11
14
b1100 #
b1100 &
#173
b111 !
b111 =
1/
b1101 #
b1101 &
#174
1*
1)
15
b1000 !
b1000 =
1,
0/
01
b1110 #
b1110 &
#175
b1001 !
b1001 =
1/
b1111 #
b1111 &
#176
0"
0*
0)
05
b1011 !
b1011 =
0,
0.
11
04
18
b0 #
b0 &
b1011 $
b1011 '
#177
1)
1(
12
b1100 !
b1100 =
1+
0/
b1 #
b1 &
#178
0(
02
b1101 !
b1101 =
0+
1,
1/
01
b10 #
b10 &
#179
1(
b1110 !
b1110 =
1+
0/
b11 #
b11 &
#180
0(
0)
b1111 !
b1111 =
0+
0,
1/
11
14
b100 #
b100 &
#181
1"
1)
1*
1(
12
16
1;
b0 !
b0 =
1+
0/
b101 #
b101 &
#182
0(
15
1:
02
06
0;
b1 !
b1 =
0+
1,
1/
01
b110 #
b110 &
#183
1(
b10 !
b10 =
1+
0/
b111 #
b111 &
#184
0*
0(
0)
05
0:
b11 !
b11 =
0+
0,
1.
1/
11
04
08
b1000 #
b1000 &
#185
1)
1(
12
b100 !
b100 =
1+
0/
b1001 #
b1001 &
#186
0(
02
b101 !
b101 =
0+
1,
1/
01
b1010 #
b1010 &
#187
1(
b110 !
b110 =
1+
0/
b1011 #
b1011 &
#188
0(
0)
b111 !
b111 =
0+
0,
1/
11
14
b1100 #
b1100 &
#189
1)
1*
1(
12
16
b1000 !
b1000 =
1+
0/
b1101 #
b1101 &
#190
0(
15
02
06
b1001 !
b1001 =
0+
1,
1/
01
b1110 #
b1110 &
#191
1(
b1010 !
b1010 =
1+
0/
b1111 #
b1111 &
#192
0"
0*
b1100 !
b1100 =
0(
0)
05
0.
18
0+
0,
b0 #
b0 &
b1100 $
b1100 '
#193
b1101 !
b1101 =
1/
b1 #
b1 &
#194
b1110 !
b1110 =
0/
11
b10 #
b10 &
#195
b1111 !
b1111 =
1/
b11 #
b11 &
#196
1"
1*
19
b0 !
b0 =
1-
0/
01
04
b100 #
b100 &
#197
b1 !
b1 =
1/
b101 #
b101 &
#198
b10 !
b10 =
0/
11
b110 #
b110 &
#199
b11 !
b11 =
1/
b111 #
b111 &
#200
0*
09
b100 !
b100 =
0-
1.
0/
01
14
08
b1000 #
b1000 &
#201
b101 !
b101 =
1/
b1001 #
b1001 &
#202
b110 !
b110 =
0/
11
b1010 #
b1010 &
#203
b111 !
b111 =
1/
b1011 #
b1011 &
#204
1*
b1000 !
b1000 =
1-
0/
01
04
b1100 #
b1100 &
#205
b1001 !
b1001 =
1/
b1101 #
b1101 &
#206
b1010 !
b1010 =
0/
11
b1110 #
b1110 &
#207
b1011 !
b1011 =
1/
b1111 #
b1111 &
#208
0"
0*
b1101 !
b1101 =
0-
0.
01
14
18
b0 #
b0 &
b1101 $
b1101 '
#209
1(
b1110 !
b1110 =
1+
0/
b1 #
b1 &
#210
0(
b1111 !
b1111 =
0+
1/
11
b10 #
b10 &
#211
1"
1)
1*
1(
12
16
1;
b0 !
b0 =
1+
0/
b11 #
b11 &
#212
0)
0(
19
02
06
0;
b1 !
b1 =
0+
1-
1/
01
04
b100 #
b100 &
#213
1(
b10 !
b10 =
1+
0/
b101 #
b101 &
#214
0(
b11 !
b11 =
0+
1/
11
b110 #
b110 &
#215
1)
1(
12
b100 !
b100 =
1+
0/
b111 #
b111 &
#216
0)
0(
0*
02
09
b101 !
b101 =
0+
0-
1.
1/
01
14
08
b1000 #
b1000 &
#217
1(
b110 !
b110 =
1+
0/
b1001 #
b1001 &
#218
0(
b111 !
b111 =
0+
1/
11
b1010 #
b1010 &
#219
1)
1*
1(
12
16
b1000 !
b1000 =
1+
0/
b1011 #
b1011 &
#220
0)
0(
02
06
b1001 !
b1001 =
0+
1-
1/
01
04
b1100 #
b1100 &
#221
1(
b1010 !
b1010 =
1+
0/
b1101 #
b1101 &
#222
0(
b1011 !
b1011 =
0+
1/
11
b1110 #
b1110 &
#223
1)
1(
12
b1100 !
b1100 =
1+
0/
b1111 #
b1111 &
#224
0"
0)
0*
b1110 !
b1110 =
0(
02
0-
0.
14
18
0+
b0 #
b0 &
b1110 $
b1110 '
#225
b1111 !
b1111 =
1/
b1 #
b1 &
#226
1"
1*
1)
15
1:
b0 !
b0 =
1,
0/
01
b10 #
b10 &
#227
b1 !
b1 =
1/
b11 #
b11 &
#228
0)
19
05
0:
b10 !
b10 =
0,
1-
0/
11
04
b100 #
b100 &
#229
b11 !
b11 =
1/
b101 #
b101 &
#230
1)
b100 !
b100 =
1,
0/
01
b110 #
b110 &
#231
b101 !
b101 =
1/
b111 #
b111 &
#232
0)
0*
09
b110 !
b110 =
0,
0-
1.
0/
11
14
08
b1000 #
b1000 &
#233
b111 !
b111 =
1/
b1001 #
b1001 &
#234
1*
1)
15
b1000 !
b1000 =
1,
0/
01
b1010 #
b1010 &
#235
b1001 !
b1001 =
1/
b1011 #
b1011 &
#236
0)
05
b1010 !
b1010 =
0,
1-
0/
11
04
b1100 #
b1100 &
#237
b1011 !
b1011 =
1/
b1101 #
b1101 &
#238
1)
b1100 !
b1100 =
1,
0/
01
b1110 #
b1110 &
#239
b1101 !
b1101 =
1/
b1111 #
b1111 &
#240
0"
0)
0*
b1111 !
b1111 =
0,
0-
0.
11
14
18
b0 #
b0 &
b1111 $
b1111 '
#241
1"
1)
1*
1(
12
16
1;
b0 !
b0 =
1+
0/
b1 #
b1 &
#242
0(
15
1:
02
06
0;
b1 !
b1 =
0+
1,
1/
01
b10 #
b10 &
#243
1(
b10 !
b10 =
1+
0/
b11 #
b11 &
#244
0(
0)
19
05
0:
b11 !
b11 =
0+
0,
1-
1/
11
04
b100 #
b100 &
#245
1)
1(
12
b100 !
b100 =
1+
0/
b101 #
b101 &
#246
0(
02
b101 !
b101 =
0+
1,
1/
01
b110 #
b110 &
#247
1(
b110 !
b110 =
1+
0/
b111 #
b111 &
#248
0(
0)
0*
09
b111 !
b111 =
0+
0,
0-
1.
1/
11
14
08
b1000 #
b1000 &
#249
1)
1*
1(
12
16
b1000 !
b1000 =
1+
0/
b1001 #
b1001 &
#250
0(
15
02
06
b1001 !
b1001 =
0+
1,
1/
01
b1010 #
b1010 &
#251
1(
b1010 !
b1010 =
1+
0/
b1011 #
b1011 &
#252
0(
0)
05
b1011 !
b1011 =
0+
0,
1-
1/
11
04
b1100 #
b1100 &
#253
1)
1(
12
b1100 !
b1100 =
1+
0/
b1101 #
b1101 &
#254
0(
02
b1101 !
b1101 =
0+
1,
1/
01
b1110 #
b1110 &
#255
1(
b1110 !
b1110 =
1+
0/
b1111 #
b1111 &
#256
b0 !
b0 =
0"
0(
0)
0*
0+
0,
0-
0.
b0 #
b0 &
b0 $
b0 '
